README.md
myco_ai/__init__.py
myco_ai/__main__.py
myco_ai/cli.py
myco_ai-0.1.0.dist-info/METADATA
myco_ai-0.1.0.dist-info/WHEEL
myco_ai-0.1.0.dist-info/entry_points.txt
myco_ai-0.1.0.dist-info/RECORD
