Metadata-Version: 2.1
Name: myco-ai
Version: 0.1.0
Summary: Myco AI is a mycology assistant.
License: MIT
Keywords: app,cli,mycology,ai
Author: Mark Beacom
Author-email: m@beacom.dev
Requires-Python: >=3.8,<4.0
Classifier: License :: OSI Approved :: MIT License
Classifier: Programming Language :: Python
Classifier: Programming Language :: Python :: 3
Classifier: Programming Language :: Python :: 3.8
Classifier: Programming Language :: Python :: 3.9
Classifier: Programming Language :: Python :: 3.10
Classifier: Programming Language :: Python :: 3.11
Requires-Dist: gradio (>=3.37.0,<4.0.0)
Requires-Dist: openai (>=0.27.8,<0.28.0)
Requires-Dist: typer[all] (>=0.9.0,<0.10.0)
